hostpurge/__init__.py
hostpurge/bowtie2_mode.py
hostpurge/build_db.py
hostpurge/fastp.py
hostpurge/hostpurge.py
hostpurge/kraken2_mode.py
hostpurge-1.2.1.dist-info/LICENSE.txt
hostpurge-1.2.1.dist-info/METADATA
hostpurge-1.2.1.dist-info/WHEEL
hostpurge-1.2.1.dist-info/entry_points.txt
hostpurge-1.2.1.dist-info/top_level.txt
hostpurge-1.2.1.dist-info/RECORD
