Metadata-Version: 2.1
Name: hostpurge
Version: 1.2.1
Summary: A tool for purging host sequences from metagenomic reads
Home-page: https://github.com/HaoLuo-leo/hostpurge
Author: Hao Luo
Author-email: luohao@caas.cn
License: MIT
Requires-Python: >=3.8
License-File: LICENSE.txt
